{"entries":{"https://itunes.apple.com/us/app/parity-signer/id1218174838":{"timestamp":{"secs_since_epoch":1640810150,"nanos_since_epoch":893721545},"valid":true},"https://github.com/paritytech/parity-signer/releases/":{"timestamp":{"secs_since_epoch":1640810150,"nanos_since_epoch":857141480},"valid":true},"https://github.com/paritytech/parity-signer/tree/legacy-rust":{"timestamp":{"secs_since_epoch":1640810150,"nanos_since_epoch":840548660},"valid":true},"https://polkadot.js.org/apps":{"timestamp":{"secs_since_epoch":1640810150,"nanos_since_epoch":511940986},"valid":true},"https://github.com/bitcoin/bips/blob/master/bip-0032.mediawiki/":{"timestamp":{"secs_since_epoch":1640810152,"nanos_since_epoch":40732531},"valid":true},"https://github.com/paritytech/parity-signer/commit/ea5786c85661d9b176795b9386af640b3e73aff3":{"timestamp":{"secs_since_epoch":1640810151,"nanos_since_epoch":378516347},"valid":true},"https://github.com/maciejhirsz/uos":{"timestamp":{"secs_since_epoch":1640810150,"nanos_since_epoch":812879761},"valid":true},"https://wiki.polkadot.network/docs/en/learn-keys":{"timestamp":{"secs_since_epoch":1640810152,"nanos_since_epoch":12680328},"valid":true},"https://blog.rust-lang.org/2020/01/03/reducing-support-for-32-bit-apple-targets.html":{"timestamp":{"secs_since_epoch":1640810151,"nanos_since_epoch":101848948},"valid":true},"https://github.com/paritytech/parity-signer/releases":{"timestamp":{"secs_since_epoch":1640810151,"nanos_since_epoch":602675966},"valid":true},"https://github.com/w3f/schnorrkel":{"timestamp":{"secs_since_epoch":1640810152,"nanos_since_epoch":146743997},"valid":true},"https://play.google.com/store/apps/details?id=io.parity.signer":{"timestamp":{"secs_since_epoch":1640810150,"nanos_since_epoch":540637694},"valid":true},"https://github.com/paritytech/parity-signer/tree/legacy-metadataRN":{"timestamp":{"secs_since_epoch":1640810150,"nanos_since_epoch":828657174},"valid":true},"https://appstoreconnect.apple.com/":{"timestamp":{"secs_since_epoch":1640810151,"nanos_since_epoch":144049553},"valid":true},"https://github.com/paritytech/parity-signer/tree/legacy-4.5.3":{"timestamp":{"secs_since_epoch":1640810150,"nanos_since_epoch":968986088},"valid":true},"https://github.com/paritytech/parity-signer/tree/legacy-4.6.2":{"timestamp":{"secs_since_epoch":1640810150,"nanos_since_epoch":884777480},"valid":true},"https://polkadot.js.org/apps/":{"timestamp":{"secs_since_epoch":1640810151,"nanos_since_epoch":820684741},"valid":true},"https://github.com/paritytech/parity-signer/wiki/HDKD-on-Parity-Signer#hdkd-general-on-substrate":{"timestamp":{"secs_since_epoch":1640810152,"nanos_since_epoch":241669083},"valid":true},"https://substrate.dev/docs/en/knowledgebase/integrate/subkey":{"timestamp":{"secs_since_epoch":1640810150,"nanos_since_epoch":840030957},"valid":true},"https://developer.android.com/ndk/downloads":{"timestamp":{"secs_since_epoch":1640810151,"nanos_since_epoch":778886939},"valid":true}}}